dwave/samplers/__init__.py
dwave/samplers/py.typed
dwave/samplers/tree/solve.pyx
dwave/samplers/tree/utilities.cpp
dwave/samplers/tree/__init__.py
dwave/samplers/tree/solve.cpython-39-aarch64-linux-gnu.so
dwave/samplers/tree/solve.cpp
dwave/samplers/tree/utilities.cpython-39-aarch64-linux-gnu.so
dwave/samplers/tree/utilities.pyx
dwave/samplers/tree/orang.pxd
dwave/samplers/tree/sample.pyx
dwave/samplers/tree/sample.cpp
dwave/samplers/tree/sample.cpython-39-aarch64-linux-gnu.so
dwave/samplers/tree/samplers.py
dwave/samplers/tree/src/include/marginalizer.h
dwave/samplers/tree/src/include/utils.hpp
dwave/samplers/tree/src/include/buckettree.h
dwave/samplers/tree/src/include/base.h
dwave/samplers/tree/src/include/sample.hpp
dwave/samplers/tree/src/include/graph.h
dwave/samplers/tree/src/include/merger.h
dwave/samplers/tree/src/include/solve.hpp
dwave/samplers/tree/src/include/table.h
dwave/samplers/tree/src/include/varorder.h
dwave/samplers/tree/src/include/combine.h
dwave/samplers/tree/src/include/orang.h
dwave/samplers/tree/src/include/task.h
dwave/samplers/tree/src/include/treedecomp.h
dwave/samplers/tree/src/include/exception.h
dwave/samplers/tree/src/include/operations/min.h
dwave/samplers/tree/src/include/operations/count.h
dwave/samplers/tree/src/include/operations/logsumprod.h
dwave/samplers/tree/src/include/operations/dummy.h
dwave/samplers/greedy/decl.pxd
dwave/samplers/greedy/__init__.py
dwave/samplers/greedy/descent.pyx
dwave/samplers/greedy/descent.cpython-39-aarch64-linux-gnu.so
dwave/samplers/greedy/sampler.py
dwave/samplers/greedy/descent.cpp
dwave/samplers/greedy/composite.py
dwave/samplers/greedy/src/descent.h
dwave/samplers/greedy/src/descent.cpp
dwave/samplers/sqa/__init__.py
dwave/samplers/sqa/rotormc_annealing.pyx
dwave/samplers/sqa/pimc_annealing.cpython-39-aarch64-linux-gnu.so
dwave/samplers/sqa/rotormc_annealing.cpython-39-aarch64-linux-gnu.so
dwave/samplers/sqa/pimc_annealing.cpp
dwave_samplers-1.6.0.dist-info/METADATA
dwave_samplers-1.6.0.dist-info/WHEEL
dwave_samplers-1.6.0.dist-info/RECORD
dwave_samplers-1.6.0.dist-info/top_level.txt
dwave_samplers-1.6.0.dist-info/licenses/LICENSE
