Metadata-Version: 2.4
Name: dwave-samplers
Version: 1.6.0
Summary: Ocean-compatible collection of solvers/samplers
Home-page: https://github.com/dwavesystems/dwave-samplers
Author: D-Wave Systems Inc.
Author-email: tools@dwavesys.com
License: Apache 2.0
Project-URL: Documentation, https://docs.dwavequantum.com
Project-URL: Issue Tracker, https://github.com/dwavesystems/dwave-samplers/issues/
Project-URL: Source Code, https://github.com/dwavesystems/dwave-samplers/
Classifier: License :: OSI Approved :: Apache Software License
Classifier: Operating System :: Microsoft :: Windows
Classifier: Operating System :: POSIX
Classifier: Operating System :: Unix
Classifier: Operating System :: MacOS
Classifier: Development Status :: 4 - Beta
Classifier: Programming Language :: Python :: 3
Classifier: Programming Language :: Python :: 3 :: Only
Classifier: Programming Language :: Python :: 3.9
Classifier: Programming Language :: Python :: 3.10
Classifier: Programming Language :: Python :: 3.11
Classifier: Programming Language :: Python :: 3.12
Classifier: Programming Language :: Python :: 3.13
Classifier: Programming Language :: Python :: Implementation :: CPython
Requires-Python: >=3.9
License-File: LICENSE
Requires-Dist: numpy<3.0.0,>=1.19.0
Requires-Dist: dimod<0.13.0,>=0.12.13
Requires-Dist: networkx>=3.0
Dynamic: license-file
